{"filename":"C:\\Users\\olaru\\RiderProjects\\WeatherFunction\\__azurite_db_blob_extent__.json","collections":[{"name":"$EXTENTS_COLLECTION$","data":[{"id":"dea894d9-1c45-4425-af3d-b558c90286ca","locationId":"Default","path":"dea894d9-1c45-4425-af3d-b558c90286ca","size":121,"lastModifiedInMS":1773141600460,"meta":{"revision":2,"created":1773141600460,"version":0,"updated":1773141605226},"$loki":1,"LastModifyInMS":1773141605226},{"id":"6367c45f-77e9-4e67-a2e5-6dfcf048a48d","locationId":"Default","path":"6367c45f-77e9-4e67-a2e5-6dfcf048a48d","size":129,"lastModifiedInMS":1773144040297,"meta":{"revision":0,"created":1773144040298,"version":0},"$loki":2},{"id":"58c9504a-981c-4970-9b5c-a8aa39d6d4ac","locationId":"Default","path":"58c9504a-981c-4970-9b5c-a8aa39d6d4ac","size":234,"lastModifiedInMS":1773146828938,"meta":{"revision":3,"created":1773146828938,"version":0,"updated":1773147602055},"$loki":3,"LastModifyInMS":1773147602055}],"idIndex":[1,2,3],"binaryIndices":{"id":{"name":"id","dirty":false,"values":[2,1,0]}},"constraints":null,"uniqueNames":[],"transforms":{},"objType":"$EXTENTS_COLLECTION$","dirty":false,"cachedIndex":null,"cachedBinaryIndex":null,"cachedData":null,"adaptiveBinaryIndices":true,"transactional":false,"cloneObjects":false,"cloneMethod":"parse-stringify","asyncListeners":false,"disableMeta":false,"disableChangesApi":true,"disableDeltaChangesApi":true,"autoupdate":false,"serializableIndices":true,"disableFreeze":true,"ttl":null,"maxId":3,"DynamicViews":[],"events":{"insert":[],"update":[],"pre-insert":[],"pre-update":[],"close":[],"flushbuffer":[],"error":[],"delete":[null],"warning":[null]},"changes":[],"dirtyIds":[]}],"databaseVersion":1.5,"engineVersion":1.5,"autosave":true,"autosaveInterval":5000,"autosaveHandle":null,"throttledSaves":true,"options":{"persistenceMethod":"fs","autosave":true,"autosaveInterval":5000,"serializationMethod":"normal","destructureDelimiter":"$<\n"},"persistenceMethod":"fs","persistenceAdapter":null,"verbose":false,"events":{"init":[null],"loaded":[],"flushChanges":[],"close":[],"changes":[],"warning":[]},"ENV":"NODEJS"}